{
  "literal": "pushu",
  "katakana": [
    "プシュー",
    "プシューッ"
  ],
  "hiragana": [
    "ぷしゅー",
    "ぷしゅーっ"
  ],
  "definition": [
    {
      "meaning": "the sound of leaking air or gas, sometimes used to express embarrassment",
      "equivalent": [
        "fizz",
        "hiss",
        "psss",
        "pssshhh",
        "ssss"
      ],
      "example": [
        {
          "source": "hello_work",
          "file": "pushu-1a",
          "display": "プシューッ",
          "contributor": ""
        }
      ]
    }
  ]
}