{
  "literal": "gara",
  "katakana": [
    "ガラ",
    "ガラッ"
  ],
  "hiragana": [
    "がら",
    "がらっ"
  ],
  "definition": [
    {
      "equivalent": "bang, close, open, shut, slide, slam, swish, swoosh, thump",
      "meaning": "the sound of opening or closing a sliding window or sliding door, can be soft or slammed",
      "example": [
        "gara-1"
      ]
    },
    {
      "equivalent": "clatter, clutter, rattle, tumult",
      "meaning": "the sound of something falling apart, collapsing or settling",
      "example": [
        "gara-2"
      ]
    }
  ]
}