{
  "literal": "ahaha",
  "katakana": [
    "アハハ",
    "アハハハ",
    "アッハッハ",
    "アッハッハッハッ"
  ],
  "hiragana": [
    "あはは",
    "あははは",
    "あっはっはっ",
    "あっはっはっはっ"
  ],
  "definition": [
    {
      "refer": "",
      "type": "v",
      "meaning": "laughter, often long or repeated",
      "equivalent": [
        "ahaha",
        "cackle",
        "guffaw",
        "haha",
        "laughter",
        "snicker"
      ],
      "example": [
        {
          "source": "komi_cant_communicate",
          "file": "ahaha-1a",
          "display": "アハハ",
          "contributor": ""
        },
        {
          "source": "lord_of_the_hundred_demons",
          "file": "ahaha-1c",
          "display": "あっはっはっはっ",
          "contributor": ""
        }
      ]
    }
  ]
}