{
  "hiragana": ["ばしばし"],
  "romaji": ["bashi bashi"],
  "katakana": ["バシバシ"],
  "definition": [{
    "equivalent": [
      "bam",
      "bang",
      "crash",
      "slam",
      "slap",
      "smack",
      "thud",
      "thump",
      "thunk",
      "whack",
      "wham",
      "whap",
      "whomp"
    ],
    "refer": "bashi:1",
    "meaning": "s",
    "type": "o",
    "example": [{
      "file": "bashi_bashi-1a",
      "contributor": "",
      "display": "バシ バシ バシ",
      "source": "only_sweet_when_alone"
    }]
  }],
  "id": "bashi_bashi"
}