{
  "hiragana": [
    "だだ",
    "だだっ",
    "だっだっ",
    "だっだっだっ"
  ],
  "romaji": ["da da"],
  "katakana": [
    "ダダ",
    "ダダッ",
    "ダッダッ",
    "ダッダッダッ"
  ],
  "definition": [{
    "equivalent": [
      "bam",
      "bang",
      "boom",
      "click",
      "clickity click",
      "crack",
      "knock",
      "pop",
      "step",
      "stomp",
      "tap",
      "thump",
      "ticka tick",
      "wham"
    ],
    "refer": "",
    "meaning": "short and sharp impacts, typically rhythmic",
    "type": "o",
    "example": [
      {
        "file": "da_da-1a",
        "contributor": "",
        "display": "ダダッ",
        "source": "world_full_of_monsters"
      },
      {
        "file": "da_da-1b",
        "contributor": "",
        "display": "ダ ダ ダ ダ ダ ダ",
        "source": "saga_lagging_hero"
      },
      {
        "file": "da_da-1c",
        "contributor": "",
        "display": "ダッ ダッ ダッ",
        "source": "kaijuu_sdf"
      }
    ]
  }],
  "id": "da_da"
}