{
  "hiragana": [
    "どきゅん",
    "どきゅうん",
    "どきゅううん"
  ],
  "katakana": [
    "ドキュン",
    "ドキュウン",
    "ドキュウウン"
  ],
  "definition": [{
    "equivalent": [
      "ba-dump",
      "cute",
      "longing"
    ],
    "ref": "",
    "meaning": "the sound of a strong heartthrob, often used to indicate exaggerated cuteness or desirability",
    "id": "dokyun-1",
    "example": [{
      "file": "dokyun-1a",
      "contributor": "",
      "display": "ドキュウウン",
      "source": "isekai_sniper"
    }]
  }],
  "literal": "dokyun"
}