{
  "literal": "gabu",
  "katakana": [
    "ガブ",
    "ガブッ"
  ],
  "hiragana": [
    "がぶ",
    "がぶっ"
  ],
  "definition": [
    {
      "refer": "",
      "type": "o",
      "meaning": "a big or forceful bite, usually sudden or exaggerated",
      "equivalent": [
        "bite",
        "chomp",
        "crunch"
      ],
      "example": [
        {
          "source": "world_full_of_monsters",
          "file": "gabu-1a",
          "display": "ガブッ",
          "contributor": ""
        }
      ]
    }
  ]
}