{
  "hiragana": [
    "がき",
    "がきっ",
    "がきぃっ",
    "がきん",
    "がきんっ"
  ],
  "romaji": [
    "gaki",
    "gakin"
  ],
  "katakana": [
    "ガキ",
    "ガキッ",
    "ガキィッ",
    "ガキン",
    "ガキンッ"
  ],
  "definition": [{
    "equivalent": [
      "block",
      "clang",
      "clank",
      "clash",
      "collide",
      "crunch",
      "snap",
      "tang",
      "whang"
    ],
    "refer": "",
    "meaning": "a sharp clashing, snapping, or colliding sound",
    "type": "o",
    "example": [
      {
        "file": "gaki_gakin-1a",
        "contributor": "",
        "display": "ガキッ",
        "source": "world_full_of_monsters"
      },
      {
        "file": "gaki_gakin-1b",
        "contributor": "",
        "display": "ガキンッ",
        "source": "world_full_of_monsters"
      },
      {
        "file": "gaki_gakin-1c",
        "contributor": "",
        "display": "ガキンッ",
        "source": "neet_kunoichi"
      }
    ]
  }],
  "id": "gaki_gakin"
}