{
  "literal": "gashi",
  "katakana": [
    "ガシ",
    "ガシッ"
  ],
  "hiragana": [
    "がし",
    "がしっ"
  ],
  "definition": [
    {
      "meaning": "the act of grabbing or holding",
      "equivalent": [
        "get",
        "grab",
        "grasp",
        "grip",
        "hold",
        "nab",
        "snag"
      ],
      "example": [
        {
          "source": "world_full_of_monsters",
          "file": "gashi-1a",
          "display": "ガシッ",
          "contributor": ""
        },
        {
          "source": "peter_grill",
          "file": "gashi-1b",
          "display": "がしっ",
          "contributor": ""
        },
        {
          "source": "hone_dragon",
          "file": "gashi-1c",
          "display": "がしっ",
          "contributor": ""
        }
      ]
    }
  ]
}