{
  "literal": "giri",
  "katakana": [
    "ギリ",
    "ギリッ"
  ],
  "hiragana": [
    "ぎり",
    "ぎりっ"
  ],
  "definition": [
    {
      "refer": "gigi:1",
      "meaning": "",
      "equivalent": [
        ""
      ],
      "example": [
        {
          "source": "world_full_of_monsters",
          "file": "giri-1a",
          "display": "ギリッ",
          "contributor": ""
        },
        {
          "source": "sex_with_me_sells",
          "file": "giri-1b",
          "display": "ギリッ",
          "contributor": ""
        }
      ]
    }
  ]
}