{
  "hiragana": [
    "ごく",
    "ごくっ"
  ],
  "katakana": [
    "ゴク",
    "ゴクッ"
  ],
  "definition": [{
    "equivalent": [
      "gulp",
      "swallow"
    ],
    "meaning": "the sound of gulping or swallowing",
    "id": "goku-1",
    "example": [
      {
        "file": "goku-1a",
        "contributor": "",
        "display": "ゴクッ...",
        "source": "strongest_failure_frame"
      },
      {
        "file": "goku-1b",
        "contributor": "",
        "display": "ゴク",
        "source": "a_rank_slow_life"
      },
      {
        "file": "goku-1c",
        "contributor": "",
        "display": "ごく",
        "source": "dog_became_strongest"
      }
    ]
  }],
  "literal": "goku"
}