{
  "literal": "jun jun",
  "katakana": [
    "ジュン",
    "ジュンッ"
  ],
  "hiragana": [
    "じゅん",
    "じゅんっ"
  ],
  "definition": [
    {
      "meaning": "an indication of a dripping or oozing fluid",
      "equivalent": [
        "drip drip",
        "drop drop",
        "flow flow",
        "gush gush",
        "trickle trickle",
        "seep seep",
        "ooze ooze",
        "weep weep"
      ],
      "example": [
        {
          "source": "gyaru_academy",
          "file": "jun_jun-1a",
          "display": "ジュン♡  ジュン♡",
          "contributor": ""
        }
      ]
    }
  ]
}