{
  "literal": "kochu",
  "katakana": [
    "クチュ"
  ],
  "hiragana": [
    "くちゅ"
  ],
  "definition": [
    {
      "meaning": "the indication or sound of soft stroking or rubbing",
      "equivalent": [
        "caress",
        "fondle",
        "rub",
        "squish",
        "stroke"
      ],
      "example": [
        {
          "source": "double_play",
          "file": "kochu-1a",
          "display": "クチュ...",
          "contributor": ""
        }
      ]
    },
    {
      "meaning": "the soft sound of kissing or licking",
      "equivalent": [
        "kiss",
        "lick",
        "slurp",
        "smooch"
      ],
      "example": [
        {
          "source": "embarrassing_and_sweet",
          "file": "kochu-2a",
          "display": "くちゅ",
          "contributor": ""
        }
      ]
    }
  ]
}