{
  "literal": "kon kon",
  "katakana": [
    "コンコン",
    "コンコンッ"
  ],
  "hiragana": [
    "こんこん",
    "こんこんっ"
  ],
  "definition": [
    {
      "meaning": "the sound of someone knocking on a door",
      "equivalent": [
        "knock knock"
      ],
      "example": [
        {
          "source": "d_genesis",
          "file": "kon_kon-1a",
          "display": "コン  コン",
          "contributor": ""
        },
        {
          "source": "s_rank_behemoth",
          "file": "kon_kon-1b",
          "display": "コン  コンッ!",
          "contributor": ""
        }
      ]
    }
  ]
}