{
  "literal": "muzu muzu",
  "katakana": [
    "ムズムズ"
  ],
  "hiragana": [
    "むずむず"
  ],
  "definition": [
    {
      "refer": "",
      "type": "s",
      "meaning": "impatience, or anxious restlessness",
      "equivalent": [
        "anxious",
        "fidgety",
        "impatient",
        "nervous",
        "restless",
        "tense",
        "uneasy",
        "unnerved"
      ],
      "example": [
        {
          "source": "eternal_fool_asley",
          "file": "muzu_muzu-1a",
          "display": "ムズ  ムズ",
          "contributor": ""
        }
      ]
    }
  ]
}