{
  "hiragana": [
    "にこにこ",
    "にっこにっこ"
  ],
  "romaji": ["niko niko"],
  "katakana": [
    "ニコニコ",
    "ニッコニッコ"
  ],
  "definition": [{
    "equivalent": [""],
    "refer": "niko:1",
    "meaning": "",
    "type": "",
    "example": [
      {
        "file": "niko_niko-1a",
        "contributor": "",
        "display": "ニコ ニコ",
        "source": "komi_cant_communicate"
      },
      {
        "file": "niko_niko-1b",
        "contributor": "",
        "display": "ニッコ ニッコ",
        "source": "yojo_life"
      }
    ]
  }],
  "id": "niko_niko"
}