{
  "hiragana": [
    "にぃ",
    "にい"
  ],
  "katakana": [
    "ニィ",
    "ニイ"
  ],
  "definition": [{
    "equivalent": [
      "grin",
      "smile",
      "smirk"
    ],
    "ref": "",
    "meaning": "a mischievous or unpleasant smile",
    "id": "nyi-1",
    "example": [
      {
        "file": "nyi-1a",
        "contributor": "",
        "display": "ニィ...!",
        "source": "hello_work"
      },
      {
        "file": "nyi-1b",
        "contributor": "",
        "display": "ニィ...",
        "source": "otherworld_material_collector"
      }
    ]
  }],
  "literal": "nyi"
}