{
  "hiragana": [
    "ぺち",
    "ぺちっ"
  ],
  "katakana": [
    "ペチ",
    "ペチッ"
  ],
  "definition": [{
    "equivalent": [
      "pat",
      "slap",
      "smack",
      "spank",
      "swat",
      "tap",
      "thwack",
      "whack",
      "whap"
    ],
    "refer": "",
    "meaning": "a light slap or tap sound, usually wet or fleshy",
    "type": "o",
    "example": [{
      "file": "pechi-1a",
      "contributor": "",
      "display": "ぺちっ",
      "source": "eternal_fool_asley"
    }]
  }],
  "literal": "pechi"
}