{
  "hiragana": [
    "さら",
    "さらっ",
    "さらぁ",
    "さらぁぁ"
  ],
  "romaji": ["sara"],
  "katakana": [
    "サラ",
    "サラッ",
    "サラァ",
    "サラァァ"
  ],
  "definition": [{
    "equivalent": [
      "billow",
      "silky",
      "smooth",
      "swish",
      "swoosh",
      "whoosh"
    ],
    "refer": "",
    "meaning": "light, smooth, or silky hair, usually swishing or moving smoothly",
    "type": "s",
    "example": [
      {
        "file": "sara-1a",
        "contributor": "",
        "display": "サラ\u2026",
        "source": "komi_cant_communicate"
      },
      {
        "file": "sara-1b",
        "contributor": "",
        "display": "サラァァ",
        "source": "otherworld_material_collector"
      },
      {
        "file": "sara-1c",
        "contributor": "",
        "display": "さら\u2026",
        "source": "beastly_boys_and_girls"
      }
    ]
  }],
  "id": "sara"
}