{
  "hiragana": [
    "しゃ",
    "しゃっ",
    "しや",
    "しやっ"
  ],
  "katakana": [
    "シャ",
    "シャッ",
    "シヤ",
    "シヤッ"
  ],
  "definition": [
    {
      "equivalent": [
        "cut",
        "slice",
        "slit"
      ],
      "refer": "",
      "meaning": "the sound of cutting into something, as with a sharp knife",
      "type": "",
      "example": [{
        "file": "sha-1a",
        "contributor": "",
        "display": "シヤッ",
        "source": "kuma_kuma_kuma_bear"
      }]
    },
    {
      "equivalent": [
        "hiss",
        "shaa",
        "sss",
        "whizz"
      ],
      "refer": "",
      "meaning": "a hissing or spraying sound",
      "type": "",
      "example": [{
        "file": "sha-2a",
        "contributor": "",
        "display": "シヤー",
        "source": "double_play"
      }]
    }
  ],
  "literal": "sha"
}