{
  "hiragana": [
    "すぴ",
    "すぴー"
  ],
  "romaji": ["supi"],
  "katakana": [
    "スピ",
    "スピー"
  ],
  "definition": [{
    "equivalent": [
      "breath",
      "huff",
      "whiff",
      "zzz"
    ],
    "refer": "",
    "meaning": "soft, gentle breathing while asleep",
    "type": "v",
    "example": [
      {
        "file": "supi-1a",
        "contributor": "",
        "display": "すぴー",
        "source": "abandoned_reincarnation_sage"
      },
      {
        "file": "supi-1b",
        "contributor": "",
        "display": "すぴー",
        "source": "spy_x_family"
      }
    ]
  }],
  "id": "supi"
}