{
  "literal": "suten",
  "katakana": [
    "ステン",
    "ステーン"
  ],
  "hiragana": [
    "すてん",
    "すてーん"
  ],
  "definition": [
    {
      "meaning": "to fall from a standing position, often suddenly and involuntarily",
      "equivalent": [
        "fall",
        "slip",
        "stumble",
        "topple",
        "trip",
        "tumble"
      ],
      "example": [
        {
          "source": "different_world_smartphone",
          "file": "suten-1a",
          "display": "すてーん",
          "contributor": ""
        }
      ]
    }
  ]
}