{
  "hiragana": [
    "たたたた",
    "たたったたっ"
  ],
  "katakana": [
    "タタタタ",
    "タタッタタッ"
  ],
  "definition": [{
    "equivalent": [
      "bound",
      "dash",
      "gallop",
      "lope",
      "run",
      "sprint",
      "trot"
    ],
    "refer": "",
    "meaning": "a fast-running gait, as that of a quadruped",
    "type": "",
    "example": [{
      "file": "tata_tata-1a",
      "contributor": "",
      "display": "タタッ タタッ",
      "source": "dog_became_strongest"
    }]
  }],
  "literal": "tata tata"
}