{
  "hiragana": ["ずりずり"],
  "romaji": ["zuri zuri"],
  "katakana": ["ズリズリ"],
  "definition": [{
    "equivalent": [
      "drag",
      "lumber",
      "lurch",
      "move",
      "pull",
      "slide",
      "slip",
      "stagger",
      "stumble",
      "sway",
      "waddle"
    ],
    "refer": "",
    "meaning": "sliding, dragging or shuffling movement",
    "type": "m",
    "example": [
      {
        "file": "zuri_zuri-1a",
        "contributor": "",
        "display": "ズリズリ\u2026",
        "source": "abandoned_reincarnation_sage"
      },
      {
        "file": "zuri_zuri-1b",
        "contributor": "",
        "display": "ズリ ズリ",
        "source": "hone_dragon"
      },
      {
        "file": "zuri_zuri-1c",
        "contributor": "",
        "display": "ズリ ズリ",
        "source": "simple_sword_saint"
      }
    ]
  }],
  "id": "zuri_zuri"
}