[
  {
    "publisher_name": "KODANSHA Ltd.",
    "sources": [
      {
      "id": "abandoned_reincarnation_sage",
      "manga": "Suterareta Tensei Kenja"
      },
      {
        "id": "marginal_taylor",
        "manga": "Marginal Taylor"
      },
      {
        "id": "weakest_occupation_blacksmith",
        "manga": "Fuguushoku \"Kajishi\" dakedo Saikyou desu"
      }
    ]
  },
  {
    "publisher_name": "SHUEISHA Inc.",
    "sources": [
      {
        "id": "bungo",
        "manga": "Bungo"
      },
      {
        "id": "hikaro_no_go",
        "manga": "Hikaru no Go"
      },
      {
        "id": "spy_x_family",
        "manga": "Spy x Family"
      }
    ]
  },
  {
    "publisher_name": "KADOKAWA Corp.",
    "sources": [
      {
        "id": "d_genesis",
        "manga": "D Genesis: Dungeon ga Dekite 3-nen"
      },
      {
        "id": "different_world_smartphone",
        "manga": "Isekai wa Smartphone to Tomo ni"
      },
      {
        "id": "reincarnated_sage_daughters",
        "manga": "Tensei Kenja wa Musume to Kurasu"
      }
    ]
  },
  {
    "publisher_name": "MICRO MAGAZINE, Inc.",
    "sources": [
      {
        "id": "dog_became_strongest",
        "manga": "Isekai Tensei Shitara Aiken ga Saikyou ni Narimashita"
      },
      {
        "id": "rise_of_the_outlaw_tamer",
        "manga": "Dappou Tamer no Nariagari Boukentan"
      }
    ]
  },
  {
    "publisher_name": "AKITA PUBLISHING Co., Ltd.",
    "sources": [
      {
        "id": "hanako_24th_ward",
        "manga": "24-ku no Hanako-san"
      },
      {
        "id": "lord_of_the_hundred_demons",
        "manga": "Hyakuma No Aruji"
      },
      {
        "id": "dungeon_dining_room",
        "manga": "Meikyuu Shokudou Maou Iwaya e Youkoso "
      }
    ]
  },
  {
    "publisher_name": "KILL TIME COMMUNICATION PUBLISHING Co.",
    "sources": [
      {
        "id": "hello_work",
        "manga": "NEET dakedo Hello Work ni Ittara Isekai ni Tsuretekareta"
      },
      {
        "id": "drawing",
        "manga": "Drawing: Saikyou Mangaka wa Oekaki Skill de Isekai Musou Suru!"
      }
    ]
  },
  {
    "publisher_name": "Shogakukan Inc.",
    "sources": [
      {
        "id": "komi_cant_communicate",
        "manga": "Komi-san wa Komyushou Desu"
      },
      {
        "id": "isekai_pickup",
        "manga": "Isekai Nanpa"
      }
    ]
  },
  {
    "publisher_name": "SHUFU TO SEIKATSU SHA Co., Ltd.",
    "sources": [
      {
        "id": "kuma_kuma_kuma_bear",
        "manga": "Kuma Kuma Kuma Bear"
      },
      {
        "id": "simple_sword_saint",
        "manga": "Jimi na Kensei wa Sore Demo Saikyou Desu"
      }
    ]
  },
  {
    "publisher_name": "OVERLAP, Inc.",
    "sources": [
      {
        "id": "modern_dungeon_capture",
        "manga": "Koware Skill de Hajimeru Gendai Dungeon Kouryaku"
      },
      {
        "id": "strongest_failure_frame",
        "manga": "Hazure Waku no [Joutai Ijou Skill] de Saikyou..."
      },
      {
        "id": "hero_or_demon_king",
        "manga": "Ikitsuku saki wa yūsha ka maō ka moto hai pureiyā ga sei ku i sekai kōryaku-ki"
      },
      {
        "id": "fushi_no_kami",
        "manga": "Fushi no Kami: Henkyou kara Hajimeru Bunmei Saiseiki"
      }
    ]
  },
  {
    "publisher_name": "AlphaPolis Co., Ltd.",
    "sources": [
      {
        "id": "otherworld_material_collector",
        "manga": "Souzai Saishuka no Isekai Ryokouki"
      }
    ]
  },
  {
    "publisher_name": "MAG Garden Corp.",
    "sources": [
      {
        "id": "reincarnated_aristocrat",
        "manga": "Tensei Kizoku no Isekai Boukenroku"
      },
      {
        "id": "hone_dragon",
        "manga": "Hone Dragon no Mana Musume"
      }
    ]
  },
  {
    "publisher_name": "No9, Inc",
    "sources": [
      {
        "id": "reincarnated_farm_girl",
        "manga": "Tensei Shitara Mura Musume Datta"
      },
      {
        "id": "nete_kunoichi",
        "manga": "Neet Kunoichi to Nazeka Dousei Hajimemashita"
      },
      {
        "id": "isekai_av_filming",
        "manga": "Isekai AV Satsueitai"
      }
    ]
  },
  {
    "publisher_name": "SQUARE ENIX Co., Ltd.",
    "sources": [
      {
        "id": "world_full_of_monsters",
        "manga": "Monster ga Afureru Sekai ni Natta Node"
      }
    ]
  },
  {
    "publisher_name": "HAKUSENSHA",
    "sources": [
      {
        "id": "s_rank_behemoth",
        "manga": "S-Rank Monster no “Behemoth” Dakedo"
      },
      {
        "id": "rock_n_roll_ladies",
        "manga": "Rock wa Shukujo no Tashinami de shite"
      }
    ]
  },
  {
    "publisher_name": "Futabasha Ltd.",
    "sources": [
      {
        "id": "a_rank_slow_life",
        "manga": "A-Rank Boukensha no Slow Life"
      },
      {
        "id": "strongest_magician_was_human",
        "manga": "Maou Gun Saikyou no Majutsushi wa Ningen datta"
      },
      {
        "id": "peter_grill",
        "manga": "Peter Grill to Kenja no Jikan"
      }
    ]
  },
  {
    "publisher_name": "Coamix Inc.",
    "sources": [
      {
        "id": "strongest_thread_master",
        "manga": "Saikyou no Ito Tsukai wa Fukushuu no Shinigami ni Naru"
      },
      {
        "id": "isekai_territory_reform",
        "manga": "Isekai Ryochi Kaikaku"
      }
    ]
  },
  {
    "publisher_name": "EARTH STAR Entertainment",
    "sources": [
      {
        "id": "eternal_fool_asley",
        "manga": "Yuukyuu no Gusha Asley no, Kenja no Susume"
      },
      {
        "id": "reincarnated_as_a_dragon_egg",
        "manga": "Tensei Shitara Dragon no Tamago Datta"
      }
    ]
  }
]
